{"result":{"id":"EMPR-00000000209","es":{"nombre":"Castillo del Condestable S.L.","miniDescripcion":"","descripcion":"&nbsp;<br><div style=\"text-align: justify\">Castillo del Condestable est&aacute; especializado en el turismo cultural activo y responsable, y desarrollamos nuestra actividad en la zona del Parque Regional de Gredos y los Valles del T&iacute;etar y del Alberche.<br \/>\r\n<br \/>\r\nOfrecemos un servicio de calidad y personalizado, bajo los criterios del Turismo Responsable.<br \/>\r\n<br \/>\r\nDeseamos que nuestros clientes disfruten de unas vivencias y unas experiencias &uacute;nicas, comparti&eacute;ndolas con los habitantes de la zona, conociendo sus formas de vida tradicionales, pudiendo, a la vez, realizar actividades l&uacute;dicas y recreativas.<\/div><br>&nbsp;","caracteristica":"&nbsp;<br>&nbsp;<br>&nbsp;"},"en":{"nombre":"Castillo del Condestable S.L.","miniDescripcion":"","descripcion":"&nbsp;<br><div style=\"text-align: justify\">Castillo del Condestable est&aacute; especializado en el turismo cultural activo y responsable, y desarrollamos nuestra actividad en la zona del Parque Regional de Gredos y los Valles del T&iacute;etar y del Alberche.<br \/>\r\n<br \/>\r\nOfrecemos un servicio de calidad y personalizado, bajo los criterios del Turismo Responsable.<br \/>\r\n<br \/>\r\nDeseamos que nuestros clientes disfruten de unas vivencias y unas experiencias &uacute;nicas, comparti&eacute;ndolas con los habitantes de la zona, conociendo sus formas de vida tradicionales, pudiendo, a la vez, realizar actividades l&uacute;dicas y recreativas.<\/div><br>&nbsp;","caracteristica":"&nbsp;<br>&nbsp;<br>&nbsp;"},"imagenDestacada":null,"tlfn":"91 862 84 08","movil":"","email":"admin@castillodelcondestable.net","web":"www.castillodelcondestable.wordpress.com","redes_sociales":"&nbsp;","multimedia":null,"categoria":[{"id":"cat_4"}],"subcategorias":[{"id":"subcat_9"}],"destacado":null,"direccion":"Avda. Costa de Madrid, 5, San Mart\u00edn de Valdeiglesias (Madrid) C.P. 28680","municipio":null,"geolocalizacion":"(40.3625, -5.142541667)17","QRlink":"points.html?id=EMPR-00000000209","cajonSastre":null,"activo":"si"}}