{"result":{"id":"EMPR-00000000091","es":{"nombre":"Paintball Ti\u00e9tar","miniDescripcion":"","descripcion":"&nbsp;<br>&nbsp;<br>&nbsp;","caracteristica":"&nbsp;<br>&nbsp;<br>&nbsp;"},"en":{"nombre":"Paintball Ti\u00e9tar","miniDescripcion":"","descripcion":"&nbsp;<br>&nbsp;<br>&nbsp;","caracteristica":"&nbsp;<br>&nbsp;<br>&nbsp;"},"imagenDestacada":null,"tlfn":"607755688","movil":"","email":"info@paintballtietar.com","web":"http:\/\/www.paintballtietar.com\/","redes_sociales":"&nbsp;","multimedia":null,"categoria":[{"id":"cat_4"}],"subcategorias":[{"id":"subcat_9"}],"destacado":null,"direccion":"C\/ San Sebasti\u00e1n, 59 C.P. 05470","municipio":"Pedro Bernardo","geolocalizacion":"(40.2413126, -4.917025800000033)17","QRlink":"points.html?id=EMPR-00000000091","cajonSastre":null,"activo":"si"}}