{"result":{"id":"LUGA-00000000063","es":{"nombre":"Casta\u00f1o (A11)","miniDescripcion":"","descripcion":"<p>Especie: <em>Castanea sativa<\/em><br \/>\n<strong>Nombre vulgar: <\/strong>Casta&ntilde;o<br \/>\n<br \/>\n<strong>Altitud:<\/strong> 686m<br \/>\n<strong>Altura:<\/strong> 17m<br \/>\n<strong>E 1:15&nbsp;<\/strong> base = -2m \/ copa = 15m<br \/>\n<strong>Di&aacute;metro estimado:<\/strong> 1,97m<br \/>\nPer&iacute;metro normal: 6,18m<br \/>\nSuperficie&nbsp;de la copa: 153,86m2<br \/>\n<br \/>\n<strong>Estimaci&oacute;n de la edad: <\/strong>m&aacute;s de 300 a&ntilde;os.<\/p>\n\n<p><br \/>\n<strong>Pendiente: <\/strong>Alta, m&aacute;s del 40%<br \/>\n<strong>Exposici&oacute;n: <\/strong>Intermedia<br \/>\n<strong>Propiedades del suelo:<\/strong> Intermedio<br \/>\n<strong>Figura de protecci&oacute;n: <\/strong>Santuario de Chilla<br \/>\n<strong>Propiedad: <\/strong>Privada, de la Cofrad&iacute;a de los Caballeros de Chilla<br \/>\n<strong>Estado sanitario: <\/strong>Achaques de tinta<br \/>\n<br \/>\n<strong>Descripci&oacute;n del entorno: <\/strong>Se encuentra situado en los jardines del monasterio de la virgen de Chilla, que data del s. XIV<\/p>\n\n<p>Pie aislado<\/p>\n\n<p>Situado en una superficie arbolada, en un jard&iacute;n<\/p>\n\n<p>Estado de conservaci&oacute;n del entorno: bueno.<\/p>\n\n<p>&nbsp;<\/p>\n\n<p><strong>Trabajo que puede observarse:<\/strong> Limpia de chupones.<br \/>\n<br \/>\n<strong>Regeneraci&oacute;n: <\/strong>De cepa<br \/>\n<br \/>\n<strong>Amenazas: <\/strong>Presi&oacute;n humana.<br \/>\n<br \/>\n<strong>Motivo de singularidad:&nbsp; <\/strong>Edad, porte y enclave.<\/p>\n\n<p><br \/>\n&nbsp;<\/p>\n"},"en":{"nombre":"Casta\u00f1o (A11)","miniDescripcion":"","descripcion":"<p>Especie: <em>Castanea sativa<\/em><br \/>\n<strong>Nombre vulgar: <\/strong>Casta&ntilde;o<br \/>\n<br \/>\n<strong>Altitud:<\/strong> 686m<br \/>\n<strong>Altura:<\/strong> 17m<br \/>\n<strong>E 1:15&nbsp;<\/strong> base = -2m \/ copa = 15m<br \/>\n<strong>Di&aacute;metro estimado:<\/strong> 1,97m<br \/>\nPer&iacute;metro normal: 6,18m<br \/>\nSuperficie&nbsp;de la copa: 153,86m2<br \/>\n<br \/>\n<strong>Estimaci&oacute;n de la edad: <\/strong>m&aacute;s de 300 a&ntilde;os.<\/p>\n\n<p><br \/>\n<strong>Pendiente: <\/strong>Alta, m&aacute;s del 40%<br \/>\n<strong>Exposici&oacute;n: <\/strong>Intermedia<br \/>\n<strong>Propiedades del suelo:<\/strong> Intermedio<br \/>\n<strong>Figura de protecci&oacute;n: <\/strong>Santuario de Chilla<br \/>\n<strong>Propiedad: <\/strong>Privada, de la Cofrad&iacute;a de los Caballeros de Chilla<br \/>\n<strong>Estado sanitario: <\/strong>Achaques de tinta<br \/>\n<br \/>\n<strong>Descripci&oacute;n del entorno: <\/strong>Se encuentra situado en los jardines del monasterio de la virgen de Chilla, que data del s. XIV<\/p>\n\n<p>Pie aislado<\/p>\n\n<p>Situado en una superficie arbolada, en un jard&iacute;n<\/p>\n\n<p>Estado de conservaci&oacute;n del entorno: bueno.<\/p>\n\n<p>&nbsp;<\/p>\n\n<p><strong>Trabajo que puede observarse:<\/strong> Limpia de chupones.<br \/>\n<br \/>\n<strong>Regeneraci&oacute;n: <\/strong>De cepa<br \/>\n<br \/>\n<strong>Amenazas: <\/strong>Presi&oacute;n humana.<br \/>\n<br \/>\n<strong>Motivo de singularidad:&nbsp; <\/strong>Edad, porte y enclave.<\/p>\n\n<p><br \/>\n&nbsp;<\/p>\n"},"imagenDestacada":"\/resources\/galleries\/points\/LUGA-00000000063\/1.jpg","multimedia":[],"categoria":[{"id":"cat_3"}],"destacado":"","municipio":"Candeleda","geolocalizacion":"(40.1828125646105, -5.29475401111442)17","QRlink":"points.html?id=LUGA-00000000063","cajonSastre":[]}}