{"result":{"id":"LUGA-00000000186","es":{"nombre":"Despoblado de Los Llanos","miniDescripcion":"","descripcion":"<p>El despoblado de Los Llanos fue una antigua aldea medieval cuyos habitantes se especializaron desde el siglo XIII en la extracci&oacute;n y transformaci&oacute;n de mineral de hierro. A&uacute;n se pueden encontrar escorias de hierro en los caminos de la dehesa de la Tablada.<\/p>\n\n<p><br \/>\n&nbsp;<br \/>\n&nbsp;<\/p>\n"},"en":{"nombre":"Despoblado de Los Llanos","miniDescripcion":"","descripcion":"<p>El despoblado de Los Llanos fue una antigua aldea medieval cuyos habitantes se especializaron desde el siglo XIII en la extracci&oacute;n y transformaci&oacute;n de mineral de hierro. A&uacute;n se pueden encontrar escorias de hierro en los caminos de la dehesa de la Tablada.<\/p>\n\n<p><br \/>\n&nbsp;<br \/>\n&nbsp;<\/p>\n"},"imagenDestacada":"\/resources\/galleries\/points\/LUGA-00000000186\/1.jpg","multimedia":[],"categoria":[{"id":"cat_1"}],"destacado":"","municipio":"Arenas de San Pedro","geolocalizacion":"(40.1844160565, -5.0883144197)17","QRlink":"points.html?id=LUGA-00000000186","cajonSastre":[]}}