{"result":{"id":"LUGA-00000000700","es":{"nombre":"Ermita del Santo Cristo del Sepulcro","miniDescripcion":"","descripcion":"<p>Construcci&oacute;n del S. XVII inicialmente concebida como convento.<br \/>\n<br \/>\nEn su interior alberga una valiosa talla de Cristo yacente, de la escuela barroca castellana. La imagen, de gran dramatismo, ha gozado de profunda devoci&oacute;n a lo largo de los siglos.<\/p>\n\n<p>&nbsp;<\/p>\n\n<p>La ermita de Santo Cristo del Sepulcro est&aacute; situada en el casco urbano.<br \/>\n<br \/>\nLa imagen del Cristo es de la escuela de Gregorio Fern&aacute;ndez, de gran tama&ntilde;o, anatom&iacute;a exagerada y pecho deprimido.<br \/>\n<br \/>\nHay en ella cinco tablas procedentes de la iglesia en que se representa el Calvario, La Anunciaci&oacute;n, La Visitaci&oacute;n, San Ant&oacute;n y Santa Catalina, todas ellas del siglo XVI.<\/p>\n\n<p>&nbsp;<\/p>\n"},"en":{"nombre":"Ermita del Santo Cristo del Sepulcro","miniDescripcion":"","descripcion":"<p>Construcci&oacute;n del S. XVII inicialmente concebida como convento.<br \/>\n<br \/>\nEn su interior alberga una valiosa talla de Cristo yacente, de la escuela barroca castellana. La imagen, de gran dramatismo, ha gozado de profunda devoci&oacute;n a lo largo de los siglos.<\/p>\n\n<p>&nbsp;<\/p>\n\n<p>La ermita de Santo Cristo del Sepulcro est&aacute; situada en el casco urbano.<br \/>\n<br \/>\nLa imagen del Cristo es de la escuela de Gregorio Fern&aacute;ndez, de gran tama&ntilde;o, anatom&iacute;a exagerada y pecho deprimido.<br \/>\n<br \/>\nHay en ella cinco tablas procedentes de la iglesia en que se representa el Calvario, La Anunciaci&oacute;n, La Visitaci&oacute;n, San Ant&oacute;n y Santa Catalina, todas ellas del siglo XVI.<\/p>\n\n<p>&nbsp;<\/p>\n"},"imagenDestacada":"\/resources\/galleries\/points\/LUGA-00000000700\/1.jpg","multimedia":[],"categoria":[{"id":"cat_1"},{"id":"cat_2"}],"destacado":"","municipio":"Santa Mar\u00eda del Berrocal","geolocalizacion":"(40.5089963,-5.4057633)17","QRlink":"points.html?id=LUGA-00000000700","cajonSastre":[]}}