{"result":{"id":"LUGA-00000000383","es":{"nombre":"Ermita de Santa Mar\u00eda la Antigua","miniDescripcion":"","descripcion":"<p>Ermita en honor a Nuestra Se&ntilde;ora de la Antigua existente a la salida de el Herrad&oacute;n, junto la nueva carretera vecinal que asciende a la Ca&ntilde;ada.<\/p>\n\n<p><br \/>\n&nbsp;<br \/>\n&nbsp;<\/p>\n"},"en":{"nombre":"Ermita de Santa Mar\u00eda la Antigua","miniDescripcion":"","descripcion":"<p>Ermita en honor a Nuestra Se&ntilde;ora de la Antigua existente a la salida de el Herrad&oacute;n, junto la nueva carretera vecinal que asciende a la Ca&ntilde;ada.<\/p>\n\n<p><br \/>\n&nbsp;<br \/>\n&nbsp;<\/p>\n"},"imagenDestacada":"\/resources\/galleries\/points\/LUGA-00000000383\/1.jpg","multimedia":[],"categoria":[{"id":"cat_1"},{"id":"cat_2"}],"destacado":"","municipio":"Herrad\u00f3n de Pinares","geolocalizacion":"(40.605, -4.491666667)17","QRlink":"points.html?id=LUGA-00000000383","cajonSastre":[]}}