{"result":{"id":"LUGA-00000000403","es":{"nombre":"Capilla de Nuestra Se\u00f1ora del R\u00edo","miniDescripcion":"","descripcion":"<p>Dentro de la poblaci&oacute;n se encuentra la capilla de Nuestra Se&ntilde;ora del R&iacute;o, sin grandes pretensiones art&iacute;sticas, en la que se celebran normalmente los cultos religiosos.<\/p>\n\n<p><br \/>\n&nbsp;<br \/>\n&nbsp;<\/p>\n"},"en":{"nombre":"Capilla de Nuestra Se\u00f1ora del R\u00edo","miniDescripcion":"","descripcion":"<p>Dentro de la poblaci&oacute;n se encuentra la capilla de Nuestra Se&ntilde;ora del R&iacute;o, sin grandes pretensiones art&iacute;sticas, en la que se celebran normalmente los cultos religiosos.<\/p>\n\n<p><br \/>\n&nbsp;<br \/>\n&nbsp;<\/p>\n"},"imagenDestacada":"\/resources\/galleries\/points\/LUGA-00000000403\/1.jpg","multimedia":[],"categoria":[{"id":"cat_1"},{"id":"cat_2"}],"destacado":"","municipio":"Hoyos del Espino","geolocalizacion":"(40.356895, -5.177178)17","QRlink":"points.html?id=LUGA-00000000403","cajonSastre":[]}}